fritool/__init__.py
fritool/apiclient.py
fritool-1.0.2.dist-info/METADATA
fritool-1.0.2.dist-info/WHEEL
fritool-1.0.2.dist-info/top_level.txt
fritool-1.0.2.dist-info/RECORD
