Metadata-Version: 2.1
Name: fritool
Version: 1.0.2
Summary: finance resilence tool package
Home-page: https://github.com/5SigmaInc/fritool
Author: 5sigma
Author-email: Anton Shishkin <ashishkin@5sigma.co>
Project-URL: Homepage, https://github.com/5SigmaInc/fri-tool
Project-URL: Issues, https://github.com/5SigmaInc/fri-tool/issues
Classifier: Programming Language :: Python :: 3
Classifier: License :: OSI Approved :: GNU General Public License (GPL)
Classifier: Operating System :: OS Independent
Requires-Python: >=3.9
Requires-Dist: requests >=2.32.3
